niceware/__init__.py
niceware/__main__.py
niceware/wordlist.py
niceware-0.2.1.dist-info/DESCRIPTION.rst
niceware-0.2.1.dist-info/METADATA
niceware-0.2.1.dist-info/RECORD
niceware-0.2.1.dist-info/WHEEL
niceware-0.2.1.dist-info/entry_points.txt
niceware-0.2.1.dist-info/metadata.json
niceware-0.2.1.dist-info/top_level.txt
niceware-0.2.1.dist-info/zip-safe
