Metadata-Version: 2.0
Name: niceware
Version: 0.2.1
Summary: Convert cryptographic keys to human-readable phrases, or generate random-yet-memorable passphrases
Home-page: https://github.com/moreati/python-niceware
Author: Alex Willmer
Author-email: alex@moreati.org.uk
License: MIT license
Keywords: niceware diceware passphrase password encryption
Platform: UNKNOWN
Classifier: Development Status :: 2 - Pre-Alpha
Classifier: Environment :: Console
Classifier: Intended Audience :: Developers
Classifier: Intended Audience :: System Administrators
Classifier: License :: OSI Approved :: MIT License
Classifier: Natural Language :: English
Classifier: Operating System :: OS Independent
Classifier: Programming Language :: Python :: 2
Classifier: Programming Language :: Python :: 2.7
Classifier: Programming Language :: Python :: 3
Classifier: Programming Language :: Python :: 3.3
Classifier: Programming Language :: Python :: 3.4
Classifier: Programming Language :: Python :: 3.5
Classifier: Programming Language :: Python :: 3.6
Classifier: Topic :: Security
